trakcorelib/__init__.py
trakcorelib/py.typed
trakcorelib/calibration/__init__.py
trakcorelib/calibration/camera.py
trakcorelib/calibration/dlt.py
trakcorelib/calibration/multiview.py
trakcorelib/calibration/normalise.py
trakcorelib/calibration/utils.py
trakcorelib/images/__init__.py
trakcorelib/images/convert.py
trakcorelib/images/filenames.py
trakcorelib/images/operations.py
trakcorelib/images/read.py
trakcorelib/images/imagesequence/__init__.py
trakcorelib/images/imagesequence/base.py
trakcorelib/images/imagesequence/disk.py
trakcorelib/images/imagesequence/memory.py
trakcorelib/images/imagesequence/operations.py
trakcorelib/images/multiimagesequence/__init__.py
trakcorelib/images/multiimagesequence/base.py
trakcorelib/images/multiimagesequence/basic.py
trakcorelib/tests/__init__.py
trakcorelib/tests/calibration/conftest.py
trakcorelib/tests/calibration/test_camera_properties.py
trakcorelib/tests/calibration/test_dlt.py
trakcorelib/tests/calibration/test_multiview.py
trakcorelib/tests/calibration/test_normalise.py
trakcorelib/tests/calibration/test_utils.py
trakcorelib/tests/calibration/utils.py
trakcorelib/tests/images/conftest.py
trakcorelib/tests/images/test_baseimagesequence.py
trakcorelib/tests/images/test_basicmultiimagesequence.py
trakcorelib/tests/images/test_convert.py
trakcorelib/tests/images/test_directoryimagesequence.py
trakcorelib/tests/images/test_diskimagesequence.py
trakcorelib/tests/images/test_filenames.py
trakcorelib/tests/images/test_imagesequenceoperations.py
trakcorelib/tests/images/test_memoryimagesequence.py
trakcorelib/tests/images/test_operations.py
trakcorelib/tests/images/test_read.py
trakcorelib/tests/images/utils.py
trakcorelib-0.1.0.dist-info/METADATA
trakcorelib-0.1.0.dist-info/WHEEL
trakcorelib-0.1.0.dist-info/licenses/LICENCE.md
trakcorelib-0.1.0.dist-info/RECORD
