Metadata-Version: 2.4
Name: trakcorelib
Version: 0.1.0
Summary: Tracking utility library
Author-email: Antoine Cribellier <antoine.cribellier@wur.nl>, Cees Voesenek <cees.voesenek@vortech.nl>
License-Expression: LGPL-3.0-or-later
License-File: LICENCE.md
Requires-Python: >=3.9
Requires-Dist: numpy>=1.21.6
Requires-Dist: pillow>=11.2.1
Requires-Dist: pyquaternion>=0.9.9
Requires-Dist: scipy>=1.13.1
